cacheasy/__init__.py
cacheasy-0.0.6.dist-info/LICENSE
cacheasy-0.0.6.dist-info/METADATA
cacheasy-0.0.6.dist-info/WHEEL
cacheasy-0.0.6.dist-info/top_level.txt
cacheasy-0.0.6.dist-info/RECORD
