Metadata-Version: 2.1
Name: cacheasy
Version: 0.0.6
Summary: A simple package for caching python objects.
Author-email: Casper Kole <casper@voltgoed.nl>
Project-URL: Homepage, https://github.com/casper-voltgoed/cacheasy
Project-URL: Issues, https://github.com/casper-voltgoed/cacheasy/issues
Classifier: Programming Language :: Python :: 3
Classifier: License :: OSI Approved :: MIT License
Classifier: Operating System :: OS Independent
Requires-Python: >=3.10
License-File: LICENSE
Requires-Dist: python-dotenv
